sphinx_probs_rdf/__init__.py
sphinx_probs_rdf/builder.py
sphinx_probs_rdf/directives.py
sphinx_probs_rdf/postprocess.py
sphinx_probs_rdf/resolve.py
sphinx_probs_rdf/version.py
sphinx_probs_rdf/_static/system-definitions.css
sphinx_probs_rdf-0.5.0.dist-info/LICENSE
sphinx_probs_rdf-0.5.0.dist-info/METADATA
sphinx_probs_rdf-0.5.0.dist-info/WHEEL
sphinx_probs_rdf-0.5.0.dist-info/top_level.txt
sphinx_probs_rdf-0.5.0.dist-info/RECORD
