Metadata-Version: 2.1
Name: sphinx-probs-rdf
Version: 0.5.0
Summary: sphinx_probs_rdf is a sphinx extension which outputs RDF describing Processes and Objects using the PRObs ontology.
Home-page: https://github.com/ricklupton/sphinx_probs_rdf
Download-URL: https://pypi.org/project/sphinx_probs_rdf/
Author: Rick Lupton
Author-email: mail@ricklupton.name
License: BSD
Platform: any
Classifier: Intended Audience :: Developers
Classifier: Intended Audience :: Education
Classifier: License :: OSI Approved :: MIT License
Classifier: Operating System :: OS Independent
Classifier: Programming Language :: Python
Classifier: Programming Language :: Python :: 3
Classifier: Programming Language :: Python :: 3.7
Classifier: Programming Language :: Python :: 3.8
Classifier: Programming Language :: Python :: 3.9
Classifier: Framework :: Sphinx
Classifier: Framework :: Sphinx :: Extension
Classifier: Topic :: Documentation
Classifier: Topic :: Documentation :: Sphinx
Classifier: Topic :: Text Processing
Classifier: Topic :: Utilities
Requires-Python: >=3.7
License-File: LICENSE
Requires-Dist: sphinx >=4.0
Requires-Dist: rdflib <7.0,>=6.2
Provides-Extra: lint
Requires-Dist: flake8 ; extra == 'lint'
Requires-Dist: mypy ; extra == 'lint'
Provides-Extra: test
Requires-Dist: pytest ; extra == 'test'
Requires-Dist: myst-parser ; extra == 'test'
